pyispy/__init__.py
pyispy/hooks.py
pyispy/main.py
pyispy-0.1.2.dist-info/LICENSE
pyispy-0.1.2.dist-info/METADATA
pyispy-0.1.2.dist-info/WHEEL
pyispy-0.1.2.dist-info/top_level.txt
pyispy-0.1.2.dist-info/RECORD
