Metadata-Version: 2.1
Name: pyispy
Version: 0.1.2
Summary: 
Home-page: https://github.com/christopherdoyle/pyispy
Author: Christopher Doyle
License: MIT license
Keywords: pyispy
Platform: UNKNOWN
Classifier: Development Status :: 2 - Pre-Alpha
Classifier: Intended Audience :: Developers
Classifier: License :: OSI Approved :: MIT License
Classifier: Natural Language :: English
Classifier: Programming Language :: Python :: 3
Classifier: Programming Language :: Python :: 3.6
Classifier: Programming Language :: Python :: 3.7
Classifier: Programming Language :: Python :: 3.8
Requires-Python: >=3.6
Requires-Dist: dataclasses ; python_version == '3.6'
